pyunc/__init__.py
pyunc/__main__.py
pyunc/__version__.py
pyunc/cli.py
pyunc/conversion.py
pyunc/header.py
pyunc/uncfile.py
pyunc-0.6.3.dist-info/LICENSE
pyunc-0.6.3.dist-info/METADATA
pyunc-0.6.3.dist-info/WHEEL
pyunc-0.6.3.dist-info/entry_points.txt
pyunc-0.6.3.dist-info/top_level.txt
pyunc-0.6.3.dist-info/zip-safe
pyunc-0.6.3.dist-info/RECORD
