Metadata-Version: 2.1
Name: pyunc
Version: 0.6.3
Summary: Classes for reading UNC format MRI files
Home-page: https://github.com/jstutters/pyunc
Author: Jon Stutters
Author-email: j.stutters@ucl.ac.uk
License: MIT
Platform: UNKNOWN
Classifier: Development Status :: 4 - Beta
Classifier: Intended Audience :: Science/Research
Classifier: License :: OSI Approved :: MIT License
Requires-Dist: arrow
Requires-Dist: nibabel
Requires-Dist: numpy
